gorillapy/__init__.py
gorillapy/__main__.py
gorillapy-1.0.0.dist-info/METADATA
gorillapy-1.0.0.dist-info/WHEEL
gorillapy-1.0.0.dist-info/RECORD
