Metadata-Version: 2.4
Name: GorillaPy
Version: 1.0.0
Summary: The classic Gorilla.BAS game ported to Python and Pygame
Project-URL: Homepage, https://github.com/asweigart/gorillapy
Project-URL: Issues, https://github.com/asweigart/gorillapy/issues
Author-email: Al Sweigart <al@inventwithpython.com>
Classifier: Operating System :: OS Independent
Classifier: Programming Language :: Python :: 2
Classifier: Programming Language :: Python :: 3
Requires-Python: >=2.7
